{
  "id": "1137283",
  "name": "myBlog",
  "font_family": "iconfont",
  "css_prefix_text": "icon-",
  "description": "",
  "glyphs": [
    {
      "icon_id": "2155388",
      "name": "链接",
      "font_class": "lianjie",
      "unicode": "e63e",
      "unicode_decimal": 58942
    },
    {
      "icon_id": "4640803",
      "name": "标签",
      "font_class": "biaoqian",
      "unicode": "e607",
      "unicode_decimal": 58887
    },
    {
      "icon_id": "4954943",
      "name": "编辑",
      "font_class": "bianji",
      "unicode": "e65c",
      "unicode_decimal": 58972
    },
    {
      "icon_id": "6022415",
      "name": "日期",
      "font_class": "riqi",
      "unicode": "e613",
      "unicode_decimal": 58899
    },
    {
      "icon_id": "7458947",
      "name": "上下移动箭头",
      "font_class": "shangxiayidongjiantou",
      "unicode": "e66a",
      "unicode_decimal": 58986
    }
  ]
}
